analyze_folder_for_llm/__init__.py
analyze_folder_for_llm/main.py
analyze_folder_for_llm/preset.yaml
analyze_folder_for_llm-0.1.1.dist-info/LICENSE
analyze_folder_for_llm-0.1.1.dist-info/METADATA
analyze_folder_for_llm-0.1.1.dist-info/WHEEL
analyze_folder_for_llm-0.1.1.dist-info/entry_points.txt
analyze_folder_for_llm-0.1.1.dist-info/top_level.txt
analyze_folder_for_llm-0.1.1.dist-info/RECORD
