Metadata-Version: 2.1
Name: analyze-folder-for-llm
Version: 0.1.1
Summary: A tool for analyzing folder structures and content for use with large context on LLMs
Home-page: https://github.com/waveuphq/analyze-folder-for-llm
Author: jeblister
Author-email: jeblister@waveup.dev
Classifier: Development Status :: 3 - Alpha
Classifier: Intended Audience :: Developers
Classifier: License :: OSI Approved :: MIT License
Classifier: Operating System :: OS Independent
Classifier: Programming Language :: Python :: 3.9
Classifier: Programming Language :: Python :: 3.10
Classifier: Programming Language :: Python :: 3.11
Requires-Python: >=3.7
License-File: LICENSE
Requires-Dist: pydantic <3.0.0,>=2.7.4
Requires-Dist: typer <0.13.0,>=0.12.3
Requires-Dist: rich <14.0.0,>=13.7.1
Requires-Dist: pyyaml <7.0.0,>=6.0.1
Provides-Extra: dev
Requires-Dist: pytest ; extra == 'dev'
Requires-Dist: black ; extra == 'dev'
